xkfuzzy/__init__.py
xkfuzzy/membership.py
xkfuzzy-0.1.0.dist-info/licenses/LICENSE
xkfuzzy-0.1.0.dist-info/METADATA
xkfuzzy-0.1.0.dist-info/WHEEL
xkfuzzy-0.1.0.dist-info/top_level.txt
xkfuzzy-0.1.0.dist-info/RECORD
