Metadata-Version: 2.4
Name: xkfuzzy
Version: 0.1.0
Summary: A Python library for fuzzy membership calculations
Home-page: https://github.com/xkfuzzy/xkfuzzy
Author: xkfuzzy
Author-email: muhfajarags <muhfajarags@gmail.com>
License: MIT
Project-URL: Homepage, https://github.com/xkfuzzy/xkfuzzy
Project-URL: Repository, https://github.com/xkfuzzy/xkfuzzy
Project-URL: Issues, https://github.com/xkfuzzy/xkfuzzy/issues
Keywords: fuzzy,membership,logic,mathematics,ai
Classifier: Development Status :: 4 - Beta
Classifier: Intended Audience :: Developers
Classifier: License :: OSI Approved :: MIT License
Classifier: Operating System :: OS Independent
Classifier: Programming Language :: Python :: 3
Classifier: Programming Language :: Python :: 3.7
Classifier: Programming Language :: Python :: 3.8
Classifier: Programming Language :: Python :: 3.9
Classifier: Programming Language :: Python :: 3.10
Classifier: Programming Language :: Python :: 3.11
Classifier: Programming Language :: Python :: 3.12
Classifier: Topic :: Scientific/Engineering :: Mathematics
Classifier: Topic :: Software Development :: Libraries :: Python Modules
Requires-Python: >=3.7
License-File: LICENSE
Requires-Dist: numpy>=1.19.0
Provides-Extra: dev
Requires-Dist: pytest>=6.0; extra == "dev"
Requires-Dist: pytest-cov; extra == "dev"
Requires-Dist: black; extra == "dev"
Requires-Dist: flake8; extra == "dev"
Requires-Dist: mypy; extra == "dev"
Dynamic: author
Dynamic: home-page
Dynamic: license-file
Dynamic: requires-python
